{
  "platform": "nextjs",
  "code": {
    "lang": "js",
    "scheme": "blackbox",
    "reactRuntime": "classic"
  },
  "style": {
    "scheme": "css-modules",
    "defaultStyleCssFilePath": "plasmic/plasmic__default_style.module.css"
  },
  "images": {
    "scheme": "public-files",
    "publicDir": "../public",
    "publicUrlPrefix": "/"
  },
  "tokens": {
    "scheme": "theo",
    "tokensFilePath": "plasmic-tokens.theo.json"
  },
  "srcDir": "components",
  "defaultPlasmicDir": "./plasmic",
  "projects": [
    {
      "projectId": "4873twxeH88i7MYXjYktuR",
      "projectApiToken": "PdwAi80hidBIBiuI1g0rAOjmrrPsTAK1tYqOuJkm7UGJREnkMMxrLwILiY493fpK3fgaHCJ7QdzmU936LOTw",
      "projectName": "Vantage2",
      "version": "latest",
      "cssFilePath": "plasmic/vantage_2/plasmic_vantage_2.module.css",
      "components": [
        {
          "id": "7BDiKA8AHJMX",
          "name": "Homepage",
          "type": "managed",
          "projectId": "4873twxeH88i7MYXjYktuR",
          "renderModuleFilePath": "plasmic/vantage_2/PlasmicHomepage.jsx",
          "importSpec": {
            "modulePath": "../pages/index.jsx"
          },
          "cssFilePath": "plasmic/vantage_2/PlasmicHomepage.module.css",
          "scheme": "blackbox",
          "componentType": "page"
        },
        {
          "id": "nHD9Ae7fUs",
          "name": "TopPageAlert",
          "type": "managed",
          "projectId": "4873twxeH88i7MYXjYktuR",
          "renderModuleFilePath": "plasmic/vantage_2/PlasmicTopPageAlert.jsx",
          "importSpec": {
            "modulePath": "TopPageAlert.jsx"
          },
          "cssFilePath": "plasmic/vantage_2/PlasmicTopPageAlert.module.css",
          "scheme": "blackbox",
          "componentType": "component"
        },
        {
          "id": "FjEMMKSOtb",
          "name": "MyPortfolioNavLogin",
          "type": "managed",
          "projectId": "4873twxeH88i7MYXjYktuR",
          "renderModuleFilePath": "plasmic/vantage_2/PlasmicMyPortfolioNavLogin.jsx",
          "importSpec": {
            "modulePath": "MyPortfolioNavLogin.jsx"
          },
          "cssFilePath": "plasmic/vantage_2/PlasmicMyPortfolioNavLogin.module.css",
          "scheme": "blackbox",
          "componentType": "component"
        }
      ],
      "icons": [],
      "images": [],
      "indirect": false,
      "globalContextsFilePath": "",
      "codeComponents": []
    }
  ],
  "globalVariants": {
    "variantGroups": [
      {
        "id": "MybtfhPzjb6zm",
        "name": "Screen",
        "projectId": "4873twxeH88i7MYXjYktuR",
        "contextFilePath": "plasmic/vantage_2/PlasmicGlobalVariant__Screen.jsx"
      }
    ]
  },
  "wrapPagesWithGlobalContexts": true,
  "nextjsConfig": {
    "pagesDir": "../pages"
  },
  "cliVersion": "0.1.185",
  "$schema": "https://unpkg.com/@plasmicapp/cli@0.1.185/dist/plasmic.schema.json"
}
